Whatsapp_Chat_Exporter/__init__.py
Whatsapp_Chat_Exporter/__main__.py
Whatsapp_Chat_Exporter/android_crypt.py
Whatsapp_Chat_Exporter/android_handler.py
Whatsapp_Chat_Exporter/bplist.py
Whatsapp_Chat_Exporter/data_model.py
Whatsapp_Chat_Exporter/exported_handler.py
Whatsapp_Chat_Exporter/ios_handler.py
Whatsapp_Chat_Exporter/ios_media_handler.py
Whatsapp_Chat_Exporter/utility.py
Whatsapp_Chat_Exporter/vcards_contacts.py
Whatsapp_Chat_Exporter/whatsapp.html
Whatsapp_Chat_Exporter/whatsapp_old.html
whatsapp_chat_exporter-0.13.0.dist-info/licenses/LICENSE
whatsapp_chat_exporter-0.13.0.dist-info/METADATA
whatsapp_chat_exporter-0.13.0.dist-info/WHEEL
whatsapp_chat_exporter-0.13.0.dist-info/entry_points.txt
whatsapp_chat_exporter-0.13.0.dist-info/top_level.txt
whatsapp_chat_exporter-0.13.0.dist-info/RECORD
