Metadata-Version: 2.4
Name: whatsapp-chat-exporter
Version: 0.13.0
Summary: A Whatsapp database parser that provides history of your Whatsapp conversations in HTML and JSON. Android, iOS, iPadOS, Crypt12, Crypt14, Crypt15 supported.
Author-email: KnugiHK <hello@knugi.com>
License: MIT
Keywords: android,ios,parsing,history,iphone,message,crypt15,customizable,whatsapp,android-backup,messages,crypt14,crypt12,whatsapp-chat-exporter,whatsapp-export,iphone-backup,whatsapp-database,whatsapp-database-parser,whatsapp-conversations
Classifier: Programming Language :: Python :: 3 :: Only
Classifier: Programming Language :: Python :: 3.10
Classifier: Programming Language :: Python :: 3.11
Classifier: Programming Language :: Python :: 3.12
Classifier: Programming Language :: Python :: 3.13
Classifier: Programming Language :: Python :: 3.14
Classifier: License :: OSI Approved :: MIT License
Classifier: Operating System :: OS Independent
Classifier: Development Status :: 4 - Beta
Classifier: Environment :: Console
Classifier: Intended Audience :: End Users/Desktop
Classifier: Topic :: Communications :: Chat
Classifier: Topic :: Utilities
Classifier: Topic :: Database
Requires-Python: >=3.10
License-File: LICENSE
Requires-Dist: jinja2
Requires-Dist: bleach
Requires-Dist: tqdm
Provides-Extra: android-backup
Requires-Dist: pycryptodome; extra == "android-backup"
Requires-Dist: javaobj-py3; extra == "android-backup"
Provides-Extra: crypt12
Requires-Dist: pycryptodome; extra == "crypt12"
Provides-Extra: crypt14
Requires-Dist: pycryptodome; extra == "crypt14"
Provides-Extra: crypt15
Requires-Dist: pycryptodome; extra == "crypt15"
Requires-Dist: javaobj-py3; extra == "crypt15"
Provides-Extra: all
Requires-Dist: pycryptodome; extra == "all"
Requires-Dist: javaobj-py3; extra == "all"
Provides-Extra: everything
Requires-Dist: pycryptodome; extra == "everything"
Requires-Dist: javaobj-py3; extra == "everything"
Provides-Extra: backup
Requires-Dist: pycryptodome; extra == "backup"
Requires-Dist: javaobj-py3; extra == "backup"
Dynamic: license-file
